{
  "name": "t:sections.footer.name",
  "type": "footer",
  "sections": {
    "gebetswerk_footer": {
      "type": "gebetswerk-footer",
      "blocks": {
        "nav-1": {
          "type": "nav_column",
          "settings": {
            "heading": "Shop",
            "link_1_label": "Gebetsteppiche", "link_1_url": "/collections/all",
            "link_2_label": "Sets",           "link_2_url": "/collections/all",
            "link_3_label": "Gebetsketten",   "link_3_url": "/collections/all",
            "link_4_label": "Geschenkkarten", "link_4_url": "/collections/all"
          }
        },
        "nav-2": {
          "type": "nav_column",
          "settings": {
            "heading": "Service",
            "link_1_label": "Versand & Lieferung", "link_1_url": "/pages/versand",
            "link_2_label": "Rückgabe",            "link_2_url": "/pages/rueckgabe",
            "link_3_label": "FAQ",                 "link_3_url": "/pages/faq",
            "link_4_label": "Kontakt",             "link_4_url": "/pages/contact"
          }
        },
        "nav-3": {
          "type": "nav_column",
          "settings": {
            "heading": "Über",
            "link_1_label": "Unsere Geschichte", "link_1_url": "/pages/about",
            "link_2_label": "Manufaktur",        "link_2_url": "/pages/about",
            "link_3_label": "Impressum",         "link_3_url": "/pages/impressum",
            "link_4_label": "AGB",               "link_4_url": "/pages/agb",
            "link_5_label": "Datenschutz",       "link_5_url": "/pages/datenschutz"
          }
        }
      },
      "block_order": ["nav-1", "nav-2", "nav-3"],
      "settings": {
        "logo_initials": "GW",
        "brand_name": "Gebetswerk",
        "tagline": "Handgefertigte, personalisierte Gebetsteppiche – ein Geschenk, das Generationen bleibt.",
        "copyright_suffix": "Mit Liebe gefertigt.",
        "show_newsletter": true,
        "email_placeholder": "Deine E-Mail",
        "email_button": "Abonnieren",
        "email_note": "10 % Willkommensrabatt für neue Abonnenten."
      }
    }
  },
  "order": ["gebetswerk_footer"]
}
